anteater/__init__.py
anteater/main.py
anteater/src/__init__.py
anteater/src/get_lists.py
anteater/src/patch_scan.py
anteater/src/project_scan.py
anteater/src/virus_total.py
tests/__init__.py
tests/test_docopt.py
anteater-0.23.dist-info/AUTHORS.rst
anteater-0.23.dist-info/LICENSE
anteater-0.23.dist-info/METADATA
anteater-0.23.dist-info/WHEEL
anteater-0.23.dist-info/entry_points.txt
anteater-0.23.dist-info/top_level.txt
anteater-0.23.dist-info/RECORD
