Metadata-Version: 2.1
Name: anteater
Version: 0.23
Summary: Anteater - CI Validation Framework
Home-page: https://github.com/anteater/anteater
Author: Luke Hinds
Author-email: lhinds@redhat.com
License: UNKNOWN
Keywords: anteater
Platform: UNKNOWN
Classifier: Development Status :: 2 - Pre-Alpha
Classifier: Intended Audience :: Developers
Classifier: License :: OSI Approved :: Apache Software License
Classifier: Natural Language :: English
Classifier: Programming Language :: Python :: 3
Classifier: Programming Language :: Python :: Implementation :: CPython
Classifier: Programming Language :: Python :: Implementation :: PyPy
Requires-Dist: docopt
Requires-Dist: six
Requires-Dist: binaryornot
Requires-Dist: PyYAML
Requires-Dist: pylimit
Requires-Dist: redis
Requires-Dist: requests
